boards/__init__.py
boards/__main__.py
boards/app.py
boards/board.py
boards/cli.py
zillionare_ths_boards-0.2.2.dist-info/entry_points.txt
zillionare_ths_boards-0.2.2.dist-info/LICENSE
zillionare_ths_boards-0.2.2.dist-info/WHEEL
zillionare_ths_boards-0.2.2.dist-info/METADATA
zillionare_ths_boards-0.2.2.dist-info/RECORD
