Metadata-Version: 2.1
Name: zillionare-ths-boards
Version: 0.2.2
Summary: 同花顺行业板块及概念板块数据本地化
Home-page: https://github.com/zillionare/boards
License: MIT
Author: aaron yang
Author-email: aaron_yang@jieyu.ai
Requires-Python: >=3.8,<4.0
Classifier: Development Status :: 2 - Pre-Alpha
Classifier: Intended Audience :: Developers
Classifier: License :: OSI Approved :: MIT License
Classifier: Natural Language :: English
Classifier: Programming Language :: Python :: 3
Classifier: Programming Language :: Python :: 3.8
Classifier: Programming Language :: Python :: 3.9
Classifier: Programming Language :: Python :: 3.10
Classifier: Programming Language :: Python :: 3
Classifier: Programming Language :: Python :: 3.10
Classifier: Programming Language :: Python :: 3.7
Classifier: Programming Language :: Python :: 3.8
Classifier: Programming Language :: Python :: 3.9
Provides-Extra: dev
Provides-Extra: doc
Provides-Extra: test
Requires-Dist: APScheduler (>=3.9.1,<4.0.0)
Requires-Dist: akshare (>=1.7.29,<2.0.0)
Requires-Dist: arrow (>=1.2.3,<2.0.0)
Requires-Dist: black (>=22.3.0,<23.0.0); extra == "test"
Requires-Dist: fire (==0.4.0)
Requires-Dist: flake8 (==4.0.1); extra == "test"
Requires-Dist: flake8-docstrings (>=1.6.0,<2.0.0); extra == "test"
Requires-Dist: httpx (>=0.23.0,<0.24.0)
Requires-Dist: isort (==5.10.1); extra == "test"
Requires-Dist: livereload (>=2.6.3,<3.0.0)
Requires-Dist: mike (>=1.1.2,<2.0.0); extra == "doc"
Requires-Dist: mkdocs (>=1.2.3,<2.0.0); extra == "doc"
Requires-Dist: mkdocs-autorefs (>=0.3.1,<0.4.0); extra == "doc"
Requires-Dist: mkdocs-include-markdown-plugin (>=3.2.3,<4.0.0); extra == "doc"
Requires-Dist: mkdocs-material (>=8.1.11,<9.0.0); extra == "doc"
Requires-Dist: mkdocs-material-extensions (>=1.0.3,<2.0.0)
Requires-Dist: mkdocstrings (>=0.18.0,<0.19.0); extra == "doc"
Requires-Dist: pip (>=22.0.3,<23.0.0); extra == "dev"
Requires-Dist: pre-commit (>=2.17.0,<3.0.0); extra == "dev"
Requires-Dist: pyreadline (>=2.1,<3.0)
Requires-Dist: pytest (>=7.0.1,<8.0.0); extra == "test"
Requires-Dist: pytest-cov (>=3.0.0,<4.0.0); extra == "test"
Requires-Dist: retry (>=0.9.2,<0.10.0)
Requires-Dist: sanic (>=22.6.2,<23.0.0)
Requires-Dist: toml (>=0.10.2,<0.11.0); extra == "dev"
Requires-Dist: tox (>=3.24.5,<4.0.0); extra == "dev"
Requires-Dist: twine (>=3.8.0,<4.0.0); extra == "dev"
Requires-Dist: zarr (>=2.13.0,<3.0.0)
